nostril_detector/__init__.py
nostril_detector/__main__.py
nostril_detector/__version__.py
nostril_detector/ng.py
nostril_detector/ngram_data.pklz
nostril_detector/nonsense_detector.py
nostril_detector-1.2.2.data/scripts/nostril_detector
nostril_detector-1.2.2.dist-info/LICENSE
nostril_detector-1.2.2.dist-info/METADATA
nostril_detector-1.2.2.dist-info/WHEEL
nostril_detector-1.2.2.dist-info/top_level.txt
nostril_detector-1.2.2.dist-info/RECORD
