Metadata-Version: 2.1
Name: nostril-detector
Version: 1.2.2
Summary: Nonsense String Evaluator
Home-page: https://github.com/casics/nostril
Author: Michael Hucka <mhucka@caltech.edu>
Author-email: casics-team@googlegroups.com
License: GNU Lesser General Public License, version 2.1
Keywords: program-analysis text-processing gibberish-detection identifiers
Platform: any
Requires-Python: >=3
License-File: LICENSE
Requires-Dist: plac >=0.9.1
Requires-Dist: tabulate >=0.7.7
Requires-Dist: humanize >=0.5.1
Requires-Dist: pytest >=3.0.5
